masonite/oauth/OAuth.py
masonite/oauth/OAuthFacade.py
masonite/oauth/OAuthFacade.pyi
masonite/oauth/OAuthUser.py
masonite/oauth/__init__.py
masonite/oauth/config/oauth.py
masonite/oauth/drivers/AppleDriver.py
masonite/oauth/drivers/BaseDriver.py
masonite/oauth/drivers/BitbucketDriver.py
masonite/oauth/drivers/FacebookDriver.py
masonite/oauth/drivers/GithubDriver.py
masonite/oauth/drivers/GitlabDriver.py
masonite/oauth/drivers/GoogleDriver.py
masonite/oauth/drivers/__init__.py
masonite/oauth/providers/OAuthProvider.py
masonite/oauth/providers/__init__.py
masonite_oauth2-1.2.0.dist-info/LICENSE
masonite_oauth2-1.2.0.dist-info/METADATA
masonite_oauth2-1.2.0.dist-info/WHEEL
masonite_oauth2-1.2.0.dist-info/top_level.txt
masonite_oauth2-1.2.0.dist-info/RECORD
